{
	"format_version": "1.12.0",
	"minecraft:geometry": [
		{
			"description": {
				"identifier": "geometry.ammo_box3",
				"texture_width": 64,
				"texture_height": 64,
				"visible_bounds_width": 4,
				"visible_bounds_height": 2.5,
				"visible_bounds_offset": [0, 0.75, 0]
			},
			"bones": [
				{
					"name": "box",
					"pivot": [0, 0, 0],
					"cubes": [
						{"origin": [-3.5, 0, -6], "size": [7, 7, 12], "uv": [0, 0]},
						{"origin": [-3.5, 0, -6], "size": [7, 5, 2], "uv": [0, 33]},
						{"origin": [-3.5, 0, -4], "size": [7, 5, 2], "uv": [0, 33]},
						{"origin": [-3.5, 0, -2], "size": [7, 5, 2], "uv": [0, 33]}
					]
				},
				{
					"name": "bullet0",
					"parent": "box",
					"pivot": [7, 0.75, 3],
					"rotation": [0, 27.5, 0],
					"cubes": [
						{"origin": [4.5, -0.25, 2], "size": [5, 2, 2], "inflate": -0.25, "uv": [0, 44]}
					]
				},
				{
					"name": "bullet1",
					"parent": "box",
					"pivot": [7, 0.75, -5],
					"rotation": [0, -25, 0]
				},
				{
					"name": "bullet2",
					"parent": "box",
					"pivot": [0, 5.75, -4],
					"rotation": [0, -7.5, 0],
					"cubes": [
						{"origin": [-2.5, 4.75, -5], "size": [5, 2, 2], "inflate": -0.25, "uv": [0, 44]}
					]
				},
				{
					"name": "bullet3",
					"parent": "box",
					"pivot": [0, 5.75, 2],
					"rotation": [0, 52.5, 0]
				},
				{
					"name": "bullet4",
					"parent": "box",
					"pivot": [1.5, 6.75, -1.5],
					"rotation": [0, 0, -27.5]
				},
				{
					"name": "box2",
					"parent": "box",
					"pivot": [0, 7, 6],
					"rotation": [-167.5, 0, 0],
					"cubes": [
						{"origin": [-3.5, 6.5, -6], "size": [7, 2, 12], "inflate": 0.1, "uv": [0, 19]}
					]
				}
			]
		}
	]
}