{
	"format_version": "1.8.0",
	"animations": {
		"animation.slot.pull": {
			"loop": true,
			"animation_length": 0.8,
			"bones": {
				"1": {
					"rotation": {
						"0.0": [0, 0, 0],
						"0.16": [90, 0, 0],
						"0.32": [180, 0, 0],
						"0.48": [270, 0, 0],
						"0.64": [360, 0, 0],
						"0.8": [450, 0, 0]
					}
				},
				"2": {
					"rotation": {
						"0.0": [0, 0, 0],
						"0.08": [90, 0, 0],
						"0.16": [180, 0, 0],
						"0.24": [270, 0, 0],
						"0.32": [360, 0, 0],
						"0.4": [450, 0, 0],
						"0.48": [540, 0, 0],
						"0.56": [630, 0, 0],
						"0.64": [720, 0, 0],
						"0.72": [810, 0, 0],
						"0.8": [900, 0, 0]
					}
				},
				"3": {
					"rotation": {
						"0.0": [0, 0, 0],
						"0.04": [90, 0, 0],
						"0.08": [180, 0, 0],
						"0.12": [270, 0, 0],
						"0.16": [360, 0, 0],
						"0.2": [450, 0, 0],
						"0.24": [540, 0, 0],
						"0.28": [630, 0, 0],
						"0.32": [720, 0, 0],
						"0.36": [810, 0, 0],
						"0.4": [900, 0, 0],
						"0.44": [990, 0, 0],
						"0.48": [1080, 0, 0],
						"0.52": [1170, 0, 0],
						"0.56": [1260, 0, 0],
						"0.6": [1350, 0, 0],
						"0.64": [1440, 0, 0],
						"0.68": [1530, 0, 0],
						"0.72": [1620, 0, 0],
						"0.76": [1710, 0, 0],
						"0.8": [1800, 0, 0]
					}
				},
				"lever": {
					"rotation": [60, 0, 0]
				}
			},
			"sound_effects": {
			"0.0": {"effect": "clap"},
			"0.04": {"effect": "clap"},
			"0.08": {"effect": "clap"},
			"0.12": {"effect": "clap"},
			"0.16": {"effect": "clap"},
			"0.20": {"effect": "clap"},
			"0.24": {"effect": "clap"},
			"0.28": {"effect": "clap"},
			"0.32": {"effect": "clap"},
			"0.36": {"effect": "clap"},
			"0.40": {"effect": "clap"},
			"0.48": {"effect": "clap"},
			"0.52": {"effect": "clap"},
			"0.56": {"effect": "clap"},
			"0.60": {"effect": "clap"},
			"0.64": {"effect": "clap"},
			"0.68": {"effect": "clap"},
			"0.72": {"effect": "clap"},
			"0.76": {"effect": "clap"},
			"0.80": {"effect": "clap"}
			}
		}
	}
}