{
    "format_version": "1.12",
    "minecraft:recipe_shaped": {
      "description": {
      "identifier": "gunsaddon:big_bulletproof_vest"
      },
      
      "tags": [ "crafting_table" ],
      "pattern": [
        "B B",
        "CCC",
        "BCB"
      ],
      "key": {
        "B": {
          "item": "minecraft:iron_ingot"
        },
        "C": {
          "item": "minecraft:diamond"
        }
      },
      "result": {
        "item": "gunsaddon:big_bulletproof_vest",
        "count": 1
      }
    }
  }